vertezml.cp311-win_amd64.pyd
vertezml-0.0.20.dist-info/LICENSE
vertezml-0.0.20.dist-info/METADATA
vertezml-0.0.20.dist-info/WHEEL
vertezml-0.0.20.dist-info/top_level.txt
vertezml-0.0.20.dist-info/RECORD
