Metadata-Version: 2.1
Name: vertezml
Version: 0.0.20
Summary: Vertez: Statify and Infer
Author: Ravinthiran Partheepan
License-File: LICENSE
Requires-Dist: pybind11
Requires-Dist: wheel
